{
  "main": {
    "id": "ef5ce58fb0290114",
    "type": "split",
    "children": [
      {
        "id": "8bf6dbb907331437",
        "type": "tabs",
        "children": [
          {
            "id": "b427e859b414a4c5",
            "type": "leaf",
            "state": {
              "type": "markdown",
              "state": {
                "file": "README.md",
                "mode": "source",
                "source": false
              }
            }
          },
          {
            "id": "0d9ef78b5cc48e15",
            "type": "leaf",
            "state": {
              "type": "markdown",
              "state": {
                "file": "Шаблон для ADR.md",
                "mode": "source",
                "source": false
              }
            }
          },
          {
            "id": "f519048481dbf4bc",
            "type": "leaf",
            "state": {
              "type": "markdown",
              "state": {
                "file": "README.md",
                "mode": "source",
                "source": false
              }
            }
          }
        ],
        "currentTab": 2
      }
    ],
    "direction": "vertical"
  },
  "left": {
    "id": "5789a4bfd288da45",
    "type": "split",
    "children": [
      {
        "id": "bf090881fde82445",
        "type": "tabs",
        "children": [
          {
            "id": "5fb6e4360499988a",
            "type": "leaf",
            "state": {
              "type": "file-explorer",
              "state": {
                "sortOrder": "alphabetical"
              }
            }
          },
          {
            "id": "81957835b025d457",
            "type": "leaf",
            "state": {
              "type": "search",
              "state": {
                "query": "",
                "matchingCase": false,
                "explainSearch": false,
                "collapseAll": false,
                "extraContext": false,
                "sortOrder": "alphabetical"
              }
            }
          },
          {
            "id": "307b83ad4047c3a3",
            "type": "leaf",
            "state": {
              "type": "bookmarks",
              "state": {}
            }
          }
        ]
      }
    ],
    "direction": "horizontal",
    "width": 300
  },
  "right": {
    "id": "5f36e9465ef232e4",
    "type": "split",
    "children": [
      {
        "id": "bf2b80196e83bcc1",
        "type": "tabs",
        "children": [
          {
            "id": "527a33237b053586",
            "type": "leaf",
            "state": {
              "type": "backlink",
              "state": {
                "file": "README.md",
                "collapseAll": false,
                "extraContext": false,
                "sortOrder": "alphabetical",
                "showSearch": false,
                "searchQuery": "",
                "backlinkCollapsed": false,
                "unlinkedCollapsed": true
              }
            }
          },
          {
            "id": "9b1dc09fcbc7ca7d",
            "type": "leaf",
            "state": {
              "type": "outgoing-link",
              "state": {
                "file": "README.md",
                "linksCollapsed": false,
                "unlinkedCollapsed": true
              }
            }
          },
          {
            "id": "896764727e9e86ae",
            "type": "leaf",
            "state": {
              "type": "tag",
              "state": {
                "sortOrder": "frequency",
                "useHierarchy": true
              }
            }
          },
          {
            "id": "7c5c04fcc358cbab",
            "type": "leaf",
            "state": {
              "type": "outline",
              "state": {
                "file": "README.md"
              }
            }
          }
        ]
      }
    ],
    "direction": "horizontal",
    "width": 300,
    "collapsed": true
  },
  "left-ribbon": {
    "hiddenItems": {
      "switcher:Open quick switcher": false,
      "graph:Open graph view": false,
      "canvas:Create new canvas": false,
      "daily-notes:Open today's daily note": false,
      "templates:Insert template": false,
      "command-palette:Open command palette": false
    }
  },
  "active": "f519048481dbf4bc",
  "lastOpenFiles": [
    "Шаблон для ADR.md",
    "README.md",
    "Пример диаграммы.md",
    "1. Исходные сведения/Архитектурные факторы.md",
    "1. Исходные сведения"
  ]
}